README.rst
setup.py
pipsy/__init__.py
pipsy/main.py
pipsy/pipsy.py
pipsy.egg-info/PKG-INFO
pipsy.egg-info/SOURCES.txt
pipsy.egg-info/dependency_links.txt
pipsy.egg-info/entry_points.txt
pipsy.egg-info/requires.txt
pipsy.egg-info/top_level.txt